LICENSE
README.md
setup.py
lightgrid/__init__.py
lightgrid/model.py
lightgrid.egg-info/PKG-INFO
lightgrid.egg-info/SOURCES.txt
lightgrid.egg-info/dependency_links.txt
lightgrid.egg-info/not-zip-safe
lightgrid.egg-info/top_level.txt