Metadata-Version: 2.1
Name: lightgrid
Version: 2.0.5
Summary: A Fast model parameter adjustment tool
Home-page: UNKNOWN
Author: shuwei Yan
Author-email: yan_shw@dlmu.edu.cn
License: MIT
Keywords: light,grid,gridsearch,param,parameter
Platform: any
Requires-Python: >=3.5
License-File: LICENSE
